my_package/__init__.py
my_package/module1.py
my_package_formation_hello_world-0.1.dist-info/METADATA
my_package_formation_hello_world-0.1.dist-info/WHEEL
my_package_formation_hello_world-0.1.dist-info/top_level.txt
my_package_formation_hello_world-0.1.dist-info/RECORD
